{"cameraMode":{"drawMode":0,"name":"Shaded","section":"Shading Mode"},"sceneLighting":true,"audioPlay":false,"sceneViewState":{"showFog":true,"showMaterialUpdate":false,"showSkybox":true,"showFlares":true,"showImageEffects":true,"showParticleSystems":true},"in2DMode":false,"pivot":{"x":142.52294921875,"y":-308.36376953125,"z":-226.18792724609376},"rotation":{"x":-0.39498063921928408,"y":0.49709004163742068,"z":-0.27143874764442446,"w":-0.723334789276123},"size":933.6513671875,"orthographic":false}